{"id":"26BA0678-4AC2-4774-AE9F-D3C225FD191C","dataPathRelativeToProjectURL":"..\/BetterRest.csv\/","version":"1.0","createdDate":"2024-04-14T03:54:19Z","dataURL":"file:\/\/\/Users\/rubik516\/Data\/Programming\/Swift\/100-Day-of-SwiftUI\/BetterRest\/BetterRest\/model\/BetterRest.csv","dataResult":{"dataURL":"file:\/\/\/Users\/rubik516\/Data\/Programming\/Swift\/100-Day-of-SwiftUI\/BetterRest\/BetterRest\/model\/BetterRest.csv","createdDate":"2024-04-14T03:54:19Z","dataSourceID":"26BA0678-4AC2-4774-AE9F-D3C225FD191C"},"activityEntities":["dataSourceMetrics",[{"id":"B5212C60-62EE-4931-9003-E6B82253B6EC","title":"Data Summary","createdDate":"2024-04-14T03:55:50Z","event":"dataSourceMetrics","subtitle":"10,000 Items"}],"dataSourceTrainingStarted",[{"id":"32A9ABDB-5591-439D-8DCA-EB73869D5B97","title":"Used By","createdDate":"2024-04-14T03:55:50Z","event":"dataSourceTrainingStarted","subtitle":"BetterRest 1"}]],"title":"BetterRest.csv","pathType":0,"modifiedDate":"2024-04-14T03:55:50Z","preferredFilename":"BetterRest.csv","experimentIDs":["7D2C9370-2685-4845-B1FC-D27D2EBCF38C"]}